overcast_to_sqlite/__init__.py
overcast_to_sqlite/chapters_backfill.py
overcast_to_sqlite/cli.py
overcast_to_sqlite/constants.py
overcast_to_sqlite/datastore.py
overcast_to_sqlite/episode.py
overcast_to_sqlite/exceptions.py
overcast_to_sqlite/feed.py
overcast_to_sqlite/more_itertools.py
overcast_to_sqlite/overcast.py
overcast_to_sqlite/py.typed
overcast_to_sqlite/utils.py
overcast_to_sqlite/html/__init__.py
overcast_to_sqlite/html/episode.html
overcast_to_sqlite/html/episode_item.py
overcast_to_sqlite/html/htmltagfixer.py
overcast_to_sqlite/html/index.html
overcast_to_sqlite/html/mvp.css
overcast_to_sqlite/html/page.py
overcast_to_sqlite/html/search.js
overcast_to_sqlite-0.9.0.dist-info/licenses/LICENSE
overcast_to_sqlite-0.9.0.dist-info/METADATA
overcast_to_sqlite-0.9.0.dist-info/WHEEL
overcast_to_sqlite-0.9.0.dist-info/entry_points.txt
overcast_to_sqlite-0.9.0.dist-info/top_level.txt
overcast_to_sqlite-0.9.0.dist-info/RECORD
