Metadata-Version: 2.4
Name: overcast-to-sqlite
Version: 0.9.0
Summary: Save listening history and feed/episode info from Overcast to a SQLite database.
Author-email: Harold Martin <Harold.Martin@gmail.com>
Project-URL: Homepage, https://github.com/hbmartin/overcast-to-sqlite
Keywords: datasette,overcast,sqlite,podcasts,podcast,transcripts
Classifier: Development Status :: 4 - Beta
Classifier: Environment :: Console
Classifier: Framework :: Datasette
Classifier: Intended Audience :: End Users/Desktop
Classifier: Intended Audience :: Science/Research
Classifier: License :: OSI Approved :: Apache Software License
Classifier: Programming Language :: Python :: 3.11
Classifier: Programming Language :: Python :: 3.12
Classifier: Programming Language :: Python :: 3.13
Classifier: Programming Language :: Python :: 3.14
Classifier: Typing :: Typed
Requires-Python: >=3.11
License-File: LICENSE
Requires-Dist: click
Requires-Dist: podcast-chapter-tools
Requires-Dist: python-dateutil
Requires-Dist: requests
Requires-Dist: sqlite-utils
Provides-Extra: lint
Requires-Dist: pyroma; extra == "lint"
Requires-Dist: mypy; extra == "lint"
Requires-Dist: ruff; extra == "lint"
Requires-Dist: types-python-dateutil; extra == "lint"
Requires-Dist: types-requests; extra == "lint"
Requires-Dist: pytest; extra == "lint"
Requires-Dist: requests-mock; extra == "lint"
Dynamic: license-file
